datacontract.py
datacontract-0.1.0.dist-info/METADATA
datacontract-0.1.0.dist-info/WHEEL
datacontract-0.1.0.dist-info/top_level.txt
datacontract-0.1.0.dist-info/RECORD
