Metadata-Version: 2.1
Name: datacontract
Version: 0.1.0
Summary: DataContract
Classifier: Programming Language :: Python :: 3
Classifier: License :: OSI Approved :: MIT License
Classifier: Operating System :: OS Independent
Requires-Python: >=3.8
